NotifyDesk/NotifyDesk.py
NotifyDesk/__init__.py
NotifyDesk-1.0.0.dist-info/LICENSE
NotifyDesk-1.0.0.dist-info/METADATA
NotifyDesk-1.0.0.dist-info/WHEEL
NotifyDesk-1.0.0.dist-info/top_level.txt
NotifyDesk-1.0.0.dist-info/RECORD
