Metadata-Version: 2.1
Name: NotifyDesk
Version: 1.0.0
Summary: The NotifyDesk library provides an easy way to send notifications in Linux
Home-page: https://github.com/krator3/NotifyDesk
Author: krator3
Author-email: maxostapenko567@gmail.com
License: UNKNOWN
Keywords: python linux notifications notification
Platform: Linux
Classifier: Programming Language :: Python :: 3
Classifier: License :: OSI Approved :: MIT License
Classifier: Operating System :: POSIX :: Linux
Requires-Python: >=3.0
License-File: LICENSE
